autodistill_yolov11/__init__.py
autodistill_yolov11/yolov8.py
autodistill_yolov11-0.1.4.dist-info/LICENSE
autodistill_yolov11-0.1.4.dist-info/METADATA
autodistill_yolov11-0.1.4.dist-info/WHEEL
autodistill_yolov11-0.1.4.dist-info/top_level.txt
autodistill_yolov11-0.1.4.dist-info/RECORD
